pyspcwebgw/__init__.py
pyspcwebgw/area.py
pyspcwebgw/const.py
pyspcwebgw/utils.py
pyspcwebgw/websocket.py
pyspcwebgw/zone.py
pyspcwebgw-0.6.0.dist-info/LICENSE
pyspcwebgw-0.6.0.dist-info/METADATA
pyspcwebgw-0.6.0.dist-info/WHEEL
pyspcwebgw-0.6.0.dist-info/top_level.txt
pyspcwebgw-0.6.0.dist-info/RECORD
