Metadata-Version: 2.1
Name: pyspcwebgw
Version: 0.6.0
Summary: A Python library for communicating with SPC Web Gateway.
Home-page: https://github.com/mbrrg/pyspcwebgw
Author: Martin Berg
Author-email: mbrrg@users.noreply.github.com
License: MIT
Download-URL: https://github.com/mbrrg/pyspcwebgw/archive/0.6.0.zip
Keywords: spc,vanderbilt,web gateway
Platform: UNKNOWN
Classifier: Natural Language :: English
Classifier: Programming Language :: Python :: 3
Classifier: Topic :: Home Automation
Requires-Python: >=3.7
License-File: LICENSE
Requires-Dist: aiohttp
